bopomofo/__init__.py
bopomofo/__version__.py
bopomofo/dictionrary.py
bopomofo-0.1.2.dist-info/LICENSE
bopomofo-0.1.2.dist-info/METADATA
bopomofo-0.1.2.dist-info/WHEEL
bopomofo-0.1.2.dist-info/top_level.txt
bopomofo-0.1.2.dist-info/RECORD
